niagara/__init__.py
niagara/__main__.py
niagara/config.py
niagara/generic.py
niagara/packages.py
niagara/template.py
niagara-0.0.1.2.dist-info/LICENSE
niagara-0.0.1.2.dist-info/METADATA
niagara-0.0.1.2.dist-info/WHEEL
niagara-0.0.1.2.dist-info/entry_points.txt
niagara-0.0.1.2.dist-info/top_level.txt
niagara-0.0.1.2.dist-info/RECORD
