Metadata-Version: 2.1
Name: niagara
Version: 0.0.1.2
Summary: A simple ricing tool for Linux systems.
Home-page: https://github.com/ArtixLabs/Niagara
Author: kavulox
License: AGPL-3.0
Classifier: Programming Language :: Python :: 3.9
Requires-Python: >=3.9
License-File: LICENSE
Requires-Dist: requests
Requires-Dist: argparse
Requires-Dist: pygit2
Requires-Dist: termcolor
Requires-Dist: psutil
